Metadata-Version: 2.1
Name: Netstock
Version: 1.3
Summary: A package for building TCP Server and other Networking options.
Author: Hunter Mikesell
Author-email: huntermikesell84@gmail.com
License: MIT
Classifier: Programming Language :: Python
Classifier: Programming Language :: Python :: 3.11
